[
  {
    "id": "competitive-analysis",
    "name": "crowdlisten:competitive-analysis",
    "description": "Competitive intelligence through audience perception analysis. Use when comparing brands, products, or competitors in social conversations. Requires CROWDLISTEN_API_KEY.",
    "keywords": [
      "competitive",
      "intelligence",
      "audience",
      "perception",
      "analysis",
      "comparing",
      "brands",
      "products",
      "competitors",
      "social",
      "conversations",
      "crowdlisten",
      "positioning",
      "strategy",
      "market",
      "entry",
      "landscape",
      "assessment",
      "tracking",
      "competitor",
      "changes",
      "time",
      "identifying",
      "underserved",
      "segments",
      "feature",
      "identification",
      "preparing",
      "fundraising",
      "board",
      "meetings",
      "strategic",
      "reviews"
    ]
  },
  {
    "id": "content-creator",
    "name": "crowdlisten:content-creator",
    "description": "Generate SEO-optimized marketing content with brand voice analysis. Blog posts, social media, email campaigns. Use when creating any branded content.",
    "keywords": [
      "generate",
      "seo-optimized",
      "marketing",
      "content",
      "brand",
      "voice",
      "analysis",
      "blog",
      "posts",
      "social",
      "media",
      "email",
      "campaigns",
      "creating",
      "branded",
      "creator"
    ]
  },
  {
    "id": "content-strategy",
    "name": "crowdlisten:content-strategy",
    "description": "Data-driven content strategy grounded in audience demand. Topic demand analysis, content gaps, platform optimization, voice matching, campaign tracking. Requires CROWDLISTEN_API_KEY.",
    "keywords": [
      "data-driven",
      "content",
      "strategy",
      "grounded",
      "audience",
      "demand",
      "topic",
      "analysis",
      "gaps",
      "platform",
      "optimization",
      "voice",
      "matching",
      "campaign",
      "tracking",
      "crowdlisten",
      "calendar",
      "planning",
      "audience-validated",
      "topics",
      "finding",
      "competitors",
      "haven",
      "covered",
      "optimizing",
      "format",
      "timing",
      "adapting",
      "brand",
      "match",
      "communication",
      "style",
      "measuring",
      "resonance",
      "adjusting",
      "product",
      "launches",
      "performance",
      "monitoring",
      "real-time",
      "sentiment",
      "during",
      "launch",
      "windows",
      "crisis",
      "early",
      "warning",
      "message",
      "scoring"
    ]
  },
  {
    "id": "data-storytelling",
    "name": "crowdlisten:data-storytelling",
    "description": "Transform data and analysis into compelling narratives. Problem-Solution, Trend, Comparison, Hero's Journey frameworks. Use when presenting insights to stakeholders.",
    "keywords": [
      "transform",
      "data",
      "analysis",
      "compelling",
      "narratives",
      "problem-solution",
      "trend",
      "comparison",
      "hero",
      "journey",
      "frameworks",
      "presenting",
      "insights",
      "stakeholders",
      "storytelling"
    ]
  },
  {
    "id": "heuristic-evaluation",
    "name": "crowdlisten:heuristic-evaluation",
    "description": "Customer feedback analysis from social conversations. Journey friction detection, pain point mapping, persona generation, churn risk signals. Requires CROWDLISTEN_API_KEY.",
    "keywords": [
      "customer",
      "feedback",
      "analysis",
      "social",
      "conversations",
      "journey",
      "friction",
      "detection",
      "pain",
      "point",
      "mapping",
      "persona",
      "generation",
      "churn",
      "risk",
      "signals",
      "crowdlisten",
      "experience",
      "improvement",
      "optimization",
      "clustering",
      "usability",
      "signal",
      "organic",
      "discussions",
      "support",
      "strategy",
      "ticket",
      "deflection",
      "health",
      "monitoring",
      "prevention",
      "identifying",
      "profiling",
      "target",
      "audience",
      "segments",
      "heuristic",
      "evaluation"
    ]
  },
  {
    "id": "market-research-reports",
    "name": "crowdlisten:market-research",
    "description": "Generate comprehensive market research reports with Porter's Five Forces, PESTLE, SWOT, TAM/SAM/SOM, BCG Matrix. Use for market analysis, competitive landscape, industry trends.",
    "keywords": [
      "generate",
      "comprehensive",
      "market",
      "research",
      "reports",
      "porter",
      "five",
      "forces",
      "pestle",
      "swot",
      "matrix",
      "analysis",
      "competitive",
      "landscape",
      "industry",
      "trends"
    ]
  },
  {
    "id": "user-stories",
    "name": "crowdlisten:user-stories",
    "description": "Turn social listening data into product decisions. JTBD extraction, feature demand scoring, persona generation, user story generation from real audience data. Requires CROWDLISTEN_API_KEY.",
    "keywords": [
      "turn",
      "social",
      "listening",
      "data",
      "product",
      "decisions",
      "jtbd",
      "extraction",
      "feature",
      "demand",
      "scoring",
      "persona",
      "generation",
      "user",
      "story",
      "real",
      "audience",
      "crowdlisten",
      "planning",
      "roadmap",
      "prioritization",
      "discussions",
      "request",
      "analysis",
      "early-stage",
      "idea",
      "validation",
      "against",
      "stories"
    ]
  },
  {
    "id": "ux-researcher",
    "name": "crowdlisten:ux-research",
    "description": "UX research synthesis — user personas, journey maps, heuristic evaluation (Nielsen's 10), design recommendations. Use when analyzing user behavior or designing experiences.",
    "keywords": [
      "research",
      "synthesis",
      "user",
      "personas",
      "journey",
      "maps",
      "heuristic",
      "evaluation",
      "nielsen",
      "design",
      "recommendations",
      "analyzing",
      "behavior",
      "designing",
      "experiences",
      "researcher",
      "designer"
    ]
  }
]